img2table/__init__.py
img2table/document/__init__.py
img2table/document/image.py
img2table/document/pdf.py
img2table/document/base/__init__.py
img2table/document/base/rotation.py
img2table/ocr/__init__.py
img2table/ocr/aws_textract.py
img2table/ocr/azure.py
img2table/ocr/base.py
img2table/ocr/data.py
img2table/ocr/doctr.py
img2table/ocr/easyocr.py
img2table/ocr/google_vision.py
img2table/ocr/paddle.py
img2table/ocr/pdf.py
img2table/ocr/surya.py
img2table/ocr/tesseract.py
img2table/tables/__init__.py
img2table/tables/image.py
img2table/tables/metrics.py
img2table/tables/objects/__init__.py
img2table/tables/objects/cell.py
img2table/tables/objects/extraction.py
img2table/tables/objects/line.py
img2table/tables/objects/row.py
img2table/tables/objects/table.py
img2table/tables/processing/__init__.py
img2table/tables/processing/common.py
img2table/tables/processing/bordered_tables/__init__.py
img2table/tables/processing/bordered_tables/lines.py
img2table/tables/processing/bordered_tables/cells/__init__.py
img2table/tables/processing/bordered_tables/cells/deduplication.py
img2table/tables/processing/bordered_tables/cells/identification.py
img2table/tables/processing/bordered_tables/tables/__init__.py
img2table/tables/processing/bordered_tables/tables/cell_clustering.py
img2table/tables/processing/bordered_tables/tables/consecutive.py
img2table/tables/processing/bordered_tables/tables/implicit.py
img2table/tables/processing/bordered_tables/tables/semi_bordered.py
img2table/tables/processing/bordered_tables/tables/table_creation.py
img2table/tables/processing/borderless_tables/__init__.py
img2table/tables/processing/borderless_tables/columns.py
img2table/tables/processing/borderless_tables/model.py
img2table/tables/processing/borderless_tables/rows.py
img2table/tables/processing/borderless_tables/whitespaces.py
img2table/tables/processing/borderless_tables/layout/__init__.py
img2table/tables/processing/borderless_tables/layout/column_segments.py
img2table-1.4.2.dist-info/LICENSE.txt
img2table-1.4.2.dist-info/METADATA
img2table-1.4.2.dist-info/WHEEL
img2table-1.4.2.dist-info/pbr.json
img2table-1.4.2.dist-info/top_level.txt
img2table-1.4.2.dist-info/RECORD
