Metadata-Version: 2.1
Name: img2table
Version: 1.4.2
Summary: img2table is a table identification and extraction Python Library for PDF and images, based on OpenCV image processing
Home-page: https://github.com/xavctn/img2table
Author: Xavier Canton
License: MIT
Platform: UNKNOWN
Classifier: Programming Language :: Python :: 3 :: Only
Classifier: License :: OSI Approved :: MIT License
Classifier: Operating System :: OS Independent
Requires-Python: >=3.9, <3.14
Requires-Dist: polars[pandas]>=1.2
Requires-Dist: pyarrow>=7
Requires-Dist: numpy
Requires-Dist: pypdfium2==4.30.0
Requires-Dist: opencv-contrib-python-headless>=4
Requires-Dist: numba
Requires-Dist: beautifulsoup4
Requires-Dist: xlsxwriter>=3.0.6
Provides-Extra: aws
Requires-Dist: boto3; extra == "aws"
Provides-Extra: azure
Requires-Dist: azure-cognitiveservices-vision-computervision; extra == "azure"
Provides-Extra: easyocr
Requires-Dist: easyocr>=1.7.0; extra == "easyocr"
Requires-Dist: pillow>=10.0.1; extra == "easyocr"
Provides-Extra: gcp
Requires-Dist: google-cloud-vision; extra == "gcp"
Requires-Dist: requests; extra == "gcp"
Provides-Extra: paddle
Requires-Dist: paddlepaddle; extra == "paddle"
Requires-Dist: paddleocr>=2.0.6; extra == "paddle"
Provides-Extra: surya
Requires-Dist: surya-ocr>=0.15.0; python_version >= "3.10" and extra == "surya"
